lefqm/__init__.py
lefqm/__main__.py
lefqm/commandline_calculation.py
lefqm/conformator.py
lefqm/conformers.py
lefqm/constants.py
lefqm/ensembles.py
lefqm/gaussian.py
lefqm/moka.py
lefqm/nwchem.py
lefqm/omega.py
lefqm/shieldings.py
lefqm/shifts.py
lefqm/turbomole.py
lefqm/utils.py
lefqm/xtb.py
lefqm-0.4.0.dist-info/LICENSE.md
lefqm-0.4.0.dist-info/METADATA
lefqm-0.4.0.dist-info/WHEEL
lefqm-0.4.0.dist-info/entry_points.txt
lefqm-0.4.0.dist-info/top_level.txt
lefqm-0.4.0.dist-info/RECORD
