Metadata-Version: 2.1
Name: lefqm
Version: 0.4.0
Summary: QM pipeline tools to predict 19F chemical shift
Author-email: Patrick Penner <patrick@ppenner.com>
Project-URL: Homepage, https://github.com/PatrickPenner/lefshift
Project-URL: Issues, https://github.com/PatrickPenner/lefshift/issues
Classifier: Programming Language :: Python :: 3
Classifier: License :: OSI Approved :: MIT License
Classifier: License :: OSI Approved :: Apache Software License
Classifier: Operating System :: OS Independent
Requires-Python: >=3.8
License-File: LICENSE.md
Requires-Dist: lefshift >=0.5.0
Requires-Dist: numpy >=1.23.5
Requires-Dist: pandas >=1.5.2
Requires-Dist: rdkit >=2022.09.3
